{
    "@type": "Workflow",
    "triggerLimit": null,
    "name": "Pull Request > Merge",
    "aliasName": null,
    "tag": null,
    "description": "Marge the specified Pull Request if Pull Request is Approved.",
    "isActive": true,
    "debug": false,
    "singleRecordExecution": false,
    "remoteExecutableFlag": false,
    "parameters": [],
    "synchronous": false,
    "collection": "\/api\/3\/workflow_collections\/4c58fed3-9e16-451a-9528-0be2b71acda4",
    "versions": [],
    "triggerStep": "\/api\/3\/workflow_steps\/e008717c-3a72-4c96-9de3-c545dce74a3d",
    "steps": [
        {
            "@type": "WorkflowStep",
            "name": "Merge Pull Request",
            "description": null,
            "arguments": {
                "name": "GitHub",
                "config": "1c6ba20e-c429-469e-8b10-04d6300c8750",
                "params": {
                    "org": "{{vars.org_name}}",
                    "sha": "",
                    "repo": "{{vars.repo_name}}",
                    "owner": "fortisoar-cicd",
                    "repo_type": "Organization",
                    "pull_number": "{{vars.pull_number}}",
                    "commit_title": "",
                    "merge_method": "merge",
                    "commit_message": ""
                },
                "version": "1.0.0",
                "connector": "github",
                "operation": "merge_pull_request",
                "ignore_errors": false,
                "operationTitle": "Merge Pull Request",
                "pickFromTenant": false,
                "step_variables": []
            },
            "status": null,
            "top": "300",
            "left": "125",
            "stepType": "\/api\/3\/workflow_step_types\/0bfed618-0316-11e7-93ae-92361f002671",
            "group": null,
            "uuid": "08a231da-9e54-40a2-932a-8e5245a52e53"
        },
        {
            "@type": "WorkflowStep",
            "name": "JSON to HTML",
            "description": null,
            "arguments": {
                "params": {
                    "data": "[{{vars.json_issue}}]",
                    "display": "Horizontal",
                    "styling": false,
                    "template": "Stylized with row selection",
                    "row_fields": ""
                },
                "version": "3.2.3",
                "connector": "cyops_utilities",
                "operation": "json_to_html",
                "operationTitle": "Utils: Convert JSON into a HTML Table",
                "step_variables": []
            },
            "status": null,
            "top": "570",
            "left": "125",
            "stepType": "\/api\/3\/workflow_step_types\/0109f35d-090b-4a2b-bd8a-94cbc3508562",
            "group": null,
            "uuid": "0d131f85-7919-4607-b108-6efb4b7418da"
        },
        {
            "@type": "WorkflowStep",
            "name": "Update PR Reviewers",
            "description": null,
            "arguments": {
                "json_issue": "{% set ij = {} %}{% for k,v in vars.input.records[0].items() %}{% if k == \"pRStatus\" %}{% set _ = ij.update({k: \"Merged\"}) %}{% elif k == \"state\" %}{% set _ = ij.update({k: \"Closed\" }) %}{% else %}{% set _ = ij.update({k: v}) %}{% endif %}{% endfor %}{{ij}}"
            },
            "status": null,
            "top": "435",
            "left": "125",
            "stepType": "\/api\/3\/workflow_step_types\/04d0cf46-b6a8-42c4-8683-60a7eaa69e8f",
            "group": null,
            "uuid": "430bfcf4-f43d-4d03-a1cf-a6669772322e"
        },
        {
            "@type": "WorkflowStep",
            "name": "Configuration",
            "description": null,
            "arguments": {
                "issue_no": "{{(vars.input.records[0].cRNo.split(\"target='_blank'>\")[-1]).split(\"<\/a>\")[0]}}",
                "org_name": "{{vars.input.records[0].organizationName}}",
                "repo_name": "{{(vars.input.records[0].repo_url.split(\"target='_blank'>\")[-1]).split(\"<\/a>\")[0]}}",
                "new_branch": "CR-{{(vars.input.records[0].cRNo.split(\"target='_blank'>\")[-1]).split(\"<\/a>\")[0]}}",
                "pull_number": "{{(vars.input.records[0].pullRequest.split(\"target='_blank'>\")[-1]).split(\"<\/a>\")[0]}}"
            },
            "status": null,
            "top": "165",
            "left": "125",
            "stepType": "\/api\/3\/workflow_step_types\/04d0cf46-b6a8-42c4-8683-60a7eaa69e8f",
            "group": null,
            "uuid": "49992053-ac11-45c3-9199-c438661460c8"
        },
        {
            "@type": "WorkflowStep",
            "name": "No Operation",
            "description": null,
            "arguments": {
                "params": [],
                "version": "3.2.1",
                "connector": "cyops_utilities",
                "operation": "no_op",
                "operationTitle": "Utils: No Operation",
                "step_variables": []
            },
            "status": null,
            "top": "1110",
            "left": "125",
            "stepType": "\/api\/3\/workflow_step_types\/0109f35d-090b-4a2b-bd8a-94cbc3508562",
            "group": null,
            "uuid": "5a4b6f68-9834-4ee6-8f58-ace971764d37"
        },
        {
            "@type": "WorkflowStep",
            "name": "Populate PR Merged Details",
            "description": null,
            "arguments": {
                "type": "DecisionBased",
                "input": {
                    "schema": {
                        "title": "Pull Request Merged Details",
                        "description": "Pull Request {{vars.steps.Refine_Issue_Table.json_issue[0].pullRequest}} successfully merged.",
                        "inputVariables": []
                    }
                },
                "record": "",
                "agent_id": null,
                "resources": "change_requests",
                "owner_detail": {
                    "isAssigned": false
                },
                "isRecordLinked": false,
                "step_variables": [],
                "response_mapping": {
                    "options": [
                        {
                            "option": "OK",
                            "primary": true,
                            "step_iri": "\/api\/3\/workflow_steps\/5a4b6f68-9834-4ee6-8f58-ace971764d37"
                        }
                    ],
                    "duplicateOption": false
                },
                "email_notification": {
                    "enabled": false,
                    "smtpParameters": []
                }
            },
            "status": null,
            "top": "975",
            "left": "125",
            "stepType": "\/api\/3\/workflow_step_types\/fc04082a-d7dc-4299-96fb-6837b1baa0fe",
            "group": null,
            "uuid": "77bfd50f-41ac-496e-b435-4efbc482a2f7"
        },
        {
            "@type": "WorkflowStep",
            "name": "Update PR Reviewer Details in Issue",
            "description": null,
            "arguments": {
                "name": "GitHub",
                "config": "d47bdd7a-aa4e-434b-9826-515d1565b59d",
                "params": {
                    "org": "{{vars.org_name}}",
                    "body": "{{vars.steps.JSON_to_HTML.data}}",
                    "repo": "{{vars.repo_name}}",
                    "state": "",
                    "title": "",
                    "labels": "",
                    "assignees": "",
                    "milestone": "",
                    "repo_type": "Organization",
                    "issue_number": "{{vars.issue_no}}",
                    "state_reason": ""
                },
                "version": "1.0.0",
                "connector": "github",
                "operation": "update_issue",
                "operationTitle": "Update Issue",
                "pickFromTenant": false,
                "step_variables": []
            },
            "status": null,
            "top": "705",
            "left": "125",
            "stepType": "\/api\/3\/workflow_step_types\/0bfed618-0316-11e7-93ae-92361f002671",
            "group": null,
            "uuid": "df6499f2-d7ed-4a00-8f64-67fa8445ee38"
        },
        {
            "@type": "WorkflowStep",
            "name": "Start",
            "description": null,
            "arguments": {
                "route": "4be5cede-03f4-45e1-aa1f-c7caeb14aa5e",
                "title": "Approve Changes",
                "resources": [
                    "change_management"
                ],
                "inputVariables": [],
                "step_variables": {
                    "input": {
                        "params": [],
                        "records": "{{vars.input.records}}"
                    }
                },
                "displayConditions": {
                    "change_requests": {
                        "sort": [],
                        "limit": 30,
                        "logic": "OR",
                        "filters": [
                            {
                                "type": "object",
                                "field": "pRStatus",
                                "value": "\/api\/3\/picklists\/8e8d3689-92ec-4229-844b-50a45be3cd72",
                                "_value": {
                                    "@id": "\/api\/3\/picklists\/8e8d3689-92ec-4229-844b-50a45be3cd72",
                                    "itemValue": "Approved"
                                },
                                "operator": "eq"
                            }
                        ]
                    },
                    "change_management": {
                        "sort": [],
                        "limit": 30,
                        "logic": "AND",
                        "filters": [
                            {
                                "type": "object",
                                "field": "environment",
                                "value": [
                                    "\/api\/3\/picklists\/d4ff078d-7692-4737-b45b-00990e949651",
                                    "\/api\/3\/picklists\/48b9f120-34bc-4884-b886-85e82321684b",
                                    "\/api\/3\/picklists\/7c93c4a6-10b4-4806-aa20-1581d35d0dcb"
                                ],
                                "module": "environment",
                                "display": "",
                                "operator": "nin",
                                "template": "multiselectpicklist",
                                "OPERATOR_KEY": "$",
                                "displayTemplate": "",
                                "previousOperator": "nin",
                                "previousTemplate": "multiselectpicklist"
                            }
                        ]
                    }
                },
                "executeButtonText": "Execute",
                "noRecordExecution": false,
                "singleRecordExecution": true
            },
            "status": null,
            "top": "30",
            "left": "125",
            "stepType": "\/api\/3\/workflow_step_types\/f414d039-bb0d-4e59-9c39-a8f1e880b18a",
            "group": null,
            "uuid": "e008717c-3a72-4c96-9de3-c545dce74a3d"
        },
        {
            "@type": "WorkflowStep",
            "name": "Delete Branch",
            "description": null,
            "arguments": {
                "name": "GitHub",
                "config": "d47bdd7a-aa4e-434b-9826-515d1565b59d",
                "params": {
                    "org": "{{vars.org_name}}",
                    "repo": "{{vars.repo_name}}",
                    "repo_type": "Organization",
                    "branch_name": "{{vars.new_branch}}"
                },
                "version": "1.0.0",
                "connector": "github",
                "operation": "delete_branch",
                "operationTitle": "Delete Branch",
                "pickFromTenant": false,
                "step_variables": []
            },
            "status": null,
            "top": "840",
            "left": "125",
            "stepType": "\/api\/3\/workflow_step_types\/0bfed618-0316-11e7-93ae-92361f002671",
            "group": null,
            "uuid": "fdedf7fe-9438-49e7-8459-349bcb10a819"
        }
    ],
    "routes": [
        {
            "@type": "WorkflowRoute",
            "name": "Populate PR Merged Details -> No Operation",
            "targetStep": "\/api\/3\/workflow_steps\/5a4b6f68-9834-4ee6-8f58-ace971764d37",
            "sourceStep": "\/api\/3\/workflow_steps\/77bfd50f-41ac-496e-b435-4efbc482a2f7",
            "label": "OK",
            "isExecuted": false,
            "uuid": "64b0f0a6-dbb7-4115-bf72-baacc78458dd"
        },
        {
            "@type": "WorkflowRoute",
            "name": "Delete Branch -> Populate PR Merged Details",
            "targetStep": "\/api\/3\/workflow_steps\/77bfd50f-41ac-496e-b435-4efbc482a2f7",
            "sourceStep": "\/api\/3\/workflow_steps\/fdedf7fe-9438-49e7-8459-349bcb10a819",
            "label": null,
            "isExecuted": false,
            "uuid": "ca8fd8b9-7658-4996-8216-786e3622d6e3"
        },
        {
            "@type": "WorkflowRoute",
            "name": "Update PR Reviewers -> JSON to HTML",
            "targetStep": "\/api\/3\/workflow_steps\/0d131f85-7919-4607-b108-6efb4b7418da",
            "sourceStep": "\/api\/3\/workflow_steps\/430bfcf4-f43d-4d03-a1cf-a6669772322e",
            "label": null,
            "isExecuted": false,
            "uuid": "f926daf0-0d90-4015-bb02-28dbd520a9a5"
        },
        {
            "@type": "WorkflowRoute",
            "name": "JSON to HTML -> Update PR Reviewer Details in Issue",
            "targetStep": "\/api\/3\/workflow_steps\/df6499f2-d7ed-4a00-8f64-67fa8445ee38",
            "sourceStep": "\/api\/3\/workflow_steps\/0d131f85-7919-4607-b108-6efb4b7418da",
            "label": null,
            "isExecuted": false,
            "uuid": "ff5a4d01-0a87-4221-a251-78f19c7ffb1e"
        },
        {
            "@type": "WorkflowRoute",
            "name": "Configuration -> Merge Pull Request",
            "targetStep": "\/api\/3\/workflow_steps\/08a231da-9e54-40a2-932a-8e5245a52e53",
            "sourceStep": "\/api\/3\/workflow_steps\/49992053-ac11-45c3-9199-c438661460c8",
            "label": null,
            "isExecuted": false,
            "uuid": "1815b163-66b5-49ce-8a15-fb48a7ee53d2"
        },
        {
            "@type": "WorkflowRoute",
            "name": "Update PR Reviewer Details in Issue -> Delete Branch",
            "targetStep": "\/api\/3\/workflow_steps\/fdedf7fe-9438-49e7-8459-349bcb10a819",
            "sourceStep": "\/api\/3\/workflow_steps\/df6499f2-d7ed-4a00-8f64-67fa8445ee38",
            "label": null,
            "isExecuted": false,
            "uuid": "2025d50a-36ef-4a43-ac46-143f7cdd06c2"
        },
        {
            "@type": "WorkflowRoute",
            "name": "Start -> Configuration",
            "targetStep": "\/api\/3\/workflow_steps\/49992053-ac11-45c3-9199-c438661460c8",
            "sourceStep": "\/api\/3\/workflow_steps\/e008717c-3a72-4c96-9de3-c545dce74a3d",
            "label": null,
            "isExecuted": false,
            "uuid": "f928e0b0-8b5c-49cf-9cc0-25716f316809"
        },
        {
            "@type": "WorkflowRoute",
            "name": "Merge Pull Request -> Update PR Reviewers",
            "targetStep": "\/api\/3\/workflow_steps\/430bfcf4-f43d-4d03-a1cf-a6669772322e",
            "sourceStep": "\/api\/3\/workflow_steps\/08a231da-9e54-40a2-932a-8e5245a52e53",
            "label": null,
            "isExecuted": false,
            "uuid": "86454dfb-5cd4-409c-ad80-3a71d615a306"
        }
    ],
    "groups": [],
    "priority": "\/api\/3\/picklists\/2b563c61-ae2c-41c0-a85a-c9709585e3f2",
    "uuid": "73dd86f5-2dfc-445a-9191-d3073e75fdc2",
    "owners": [],
    "isPrivate": false,
    "deletedAt": null,
    "recordTags": [
        "ManualTrigger",
        "CICD"
    ]
}