{
    "@type": "Workflow",
    "triggerLimit": null,
    "name": "Save Production Settings",
    "aliasName": null,
    "tag": null,
    "description": "Save Production Settings into Source Control",
    "isActive": true,
    "debug": false,
    "singleRecordExecution": false,
    "remoteExecutableFlag": false,
    "parameters": [],
    "synchronous": false,
    "collection": "\/api\/3\/workflow_collections\/4c58fed3-9e16-451a-9528-0be2b71acda4",
    "versions": [],
    "triggerStep": "\/api\/3\/workflow_steps\/7dc16d47-79ad-418f-933f-2d6287f1cc2e",
    "steps": [
        {
            "@type": "WorkflowStep",
            "name": "Configuration",
            "description": null,
            "arguments": {
                "org_name": "{{vars.cicd_cofig.organizationName}}",
                "repo_name": "{{vars.cicd_cofig.productionSettings.split('\/')[-1]}}",
                "base_branch": "{{vars.cicd_cofig.baseBranch}}",
                "export_file_name": "FortiSOAR Production Environment Settings",
                "current_timestamp": "{{arrow.get((arrow.utcnow().int_timestamp  | int | abs)).format('YYYYMMDDHHmm')}}",
                "export_template_name": "FortiSOAR Production Environment Settings"
            },
            "status": null,
            "top": "30",
            "left": "125",
            "stepType": "\/api\/3\/workflow_step_types\/04d0cf46-b6a8-42c4-8683-60a7eaa69e8f",
            "group": null,
            "uuid": "6f463fd6-b22f-4729-83ce-36fd15c030df"
        },
        {
            "@type": "WorkflowStep",
            "name": "Get Source Control Details",
            "description": null,
            "arguments": {
                "params": {
                    "iri": "\/api\/wf\/api\/dynamic-variable\/?limit=50&name=cicd_cofig",
                    "body": "",
                    "method": "GET"
                },
                "version": "3.2.2",
                "connector": "cyops_utilities",
                "operation": "make_cyops_request",
                "operationTitle": "FSR: Make FortiSOAR API Call",
                "step_variables": {
                    "cicd_cofig": "{{vars.result.data['hydra:member'][0].value | toDict }}"
                }
            },
            "status": null,
            "top": "165",
            "left": "475",
            "stepType": "\/api\/3\/workflow_step_types\/0109f35d-090b-4a2b-bd8a-94cbc3508562",
            "group": null,
            "uuid": "7cc01162-ea13-4e60-b5d3-4f99737dd140"
        },
        {
            "@type": "WorkflowStep",
            "name": "Start",
            "description": null,
            "arguments": {
                "step_variables": {
                    "input": {
                        "params": []
                    }
                }
            },
            "status": null,
            "top": "30",
            "left": "475",
            "stepType": "\/api\/3\/workflow_step_types\/b348f017-9a94-471f-87f8-ce88b6a7ad62",
            "group": null,
            "uuid": "7dc16d47-79ad-418f-933f-2d6287f1cc2e"
        },
        {
            "@type": "WorkflowStep",
            "name": "Save FortiSOAR Settings",
            "description": null,
            "arguments": {
                "arguments": {
                    "cicd_cofig": "{{vars.cicd_cofig}}"
                },
                "apply_async": false,
                "step_variables": [],
                "pass_input_record": true,
                "workflowReference": "\/api\/3\/workflows\/69179225-e990-4112-b47b-ef9f4c877411"
            },
            "status": null,
            "top": "300",
            "left": "475",
            "stepType": "\/api\/3\/workflow_step_types\/74932bdc-b8b6-4d24-88c4-1a4dfbc524f3",
            "group": null,
            "uuid": "e076f0e9-0274-44e0-95ec-b74247411401"
        }
    ],
    "routes": [
        {
            "@type": "WorkflowRoute",
            "name": "Start -> Get Source Control Details",
            "targetStep": "\/api\/3\/workflow_steps\/7cc01162-ea13-4e60-b5d3-4f99737dd140",
            "sourceStep": "\/api\/3\/workflow_steps\/7dc16d47-79ad-418f-933f-2d6287f1cc2e",
            "label": null,
            "isExecuted": false,
            "uuid": "09edf7e4-4fda-492f-b08f-7b13e89395c8"
        },
        {
            "@type": "WorkflowRoute",
            "name": "Get Source Control Details -> Save FortiSOAR Settings",
            "targetStep": "\/api\/3\/workflow_steps\/e076f0e9-0274-44e0-95ec-b74247411401",
            "sourceStep": "\/api\/3\/workflow_steps\/7cc01162-ea13-4e60-b5d3-4f99737dd140",
            "label": null,
            "isExecuted": false,
            "uuid": "8470278f-293b-45fa-8213-0b941ecd51e1"
        }
    ],
    "groups": [],
    "priority": "\/api\/3\/picklists\/2b563c61-ae2c-41c0-a85a-c9709585e3f2",
    "uuid": "a58f22fc-e207-4fac-9c34-719efcc3df7a",
    "owners": [],
    "isPrivate": false,
    "deletedAt": null,
    "recordTags": []
}